waylay/services/resources/models/__init__.py
waylay/services/resources/models/array_must_contain_inner.py
waylay/services/resources/models/array_value_constraint.py
waylay/services/resources/models/array_value_constraint_type.py
waylay/services/resources/models/attribute_item.py
waylay/services/resources/models/batch_operation_enqueued.py
waylay/services/resources/models/batch_operation_result.py
waylay/services/resources/models/batch_operation_status_response.py
waylay/services/resources/models/batch_resource_delete_operation.py
waylay/services/resources/models/batch_resource_delete_operation_action.py
waylay/services/resources/models/batch_resource_delete_operation_action_parameters.py
waylay/services/resources/models/batch_resource_delete_operation_entity.py
waylay/services/resources/models/batch_resource_delete_operation_query.py
waylay/services/resources/models/batch_resource_operation.py
waylay/services/resources/models/batch_resource_type_delete_operation.py
waylay/services/resources/models/batch_resource_type_delete_operation_entity.py
waylay/services/resources/models/batch_resource_type_delete_operation_query.py
waylay/services/resources/models/batch_running_resource_operation.py
waylay/services/resources/models/batch_running_resource_operation_operation.py
waylay/services/resources/models/batch_running_resource_operation_operation_entity.py
waylay/services/resources/models/boolean_value_constraint.py
waylay/services/resources/models/boolean_value_constraint_type.py
waylay/services/resources/models/cascade_delete_values_inner.py
waylay/services/resources/models/changed_event.py
waylay/services/resources/models/changed_event_type.py
waylay/services/resources/models/cloud_metadata_event.py
waylay/services/resources/models/cloud_metadata_event_data.py
waylay/services/resources/models/cloud_metadata_event_data_source.py
waylay/services/resources/models/cloud_metadata_event_data_type.py
waylay/services/resources/models/constraint.py
waylay_sdk_resources_types-8.5.0.20241025.dist-info/LICENSE.txt
waylay_sdk_resources_types-8.5.0.20241025.dist-info/METADATA
waylay_sdk_resources_types-8.5.0.20241025.dist-info/WHEEL
waylay_sdk_resources_types-8.5.0.20241025.dist-info/top_level.txt
waylay_sdk_resources_types-8.5.0.20241025.dist-info/RECORD
